<?xml version="1.0" encoding="UTF-8" ?>
<!DOCTYPE struts PUBLIC "-//Apache Software Foundation//DTD Struts Configuration 2.1//EN" "http://struts.apache.org/dtds/struts-2.1.dtd">
<struts>
 	<constant name="struts.action.extension" value="do" />
	<package name="default" namespace="/" extends="struts-default"></package>
	
	<package name="xiaofang" namespace="/xiaofang" extends="json-default">
	<action name="*_*" class="action.{1}Action" method="{2}">
	 <result name="query_success">/transit-jsp/xiaofang-tr.jsp</result> 
	   <result name="add_success" type="redirect">/show/xiaofang.jsp</result> 
	   <result type="json" name="checkByDate"><param name="root">object</param></result>
	</action>
	</package>
	
	<package name="miehuo" namespace="/miehuo" extends="json-default">
	<action name="*_*" class="action.{1}Action" method="{2}">
	 <result name="query_success">/transit-jsp/miehuo-tr.jsp</result> 
	  <result name="add_success" type="redirect">/show/miehuo.jsp</result> 
	  <result type="json" name="checkByDate"><param name="root">object</param></result>
	</action>
	</package>
	
	<package name="device" namespace="/device" extends="json-default">
	<action name="*_*" class="action.{1}Action" method="{2}">
	 <result  type="json" name="ok"></result>
	 <result type="json" name="query_success"><param name="root">object</param></result>
	 
	  <result name="add_success" type="redirect">/show/miehuo.jsp</result> 
	</action>
	</package>
	
	<package name="login" namespace="/login" extends="struts-default">
	<action name="*_*" class="action.{1}Action" method="{2}">
	 
	  <result name="query_success" >/view/main/ezui.jsp</result> 
	</action>
	</package>
	
	<package name="area" namespace="/area" extends="json-default">
	<action name="*_*" class="action.{1}Action" method="{2}">
	 <result name="add_success" type="redirect">/pc/area_query.jsp</result>
	  <result type="json" name="query_success"><param name="root">object</param></result>
	   <result type="json" name="queryShuoming_success"><param name="root">object2</param></result>
	</action>
	</package>
	<package name="category" namespace="/category" extends="json-default">
	<action name="*_*" class="action.{1}Action" method="{2}">
	 <result name="add_success" type="redirect">/pc/area_query.jsp</result>
	  <result type="json" name="query_success"><param name="root">object</param></result>
	  <result type="json" name="queryLeibie_success"><param name="root">object2</param></result>
	</action>
	</package>
	
	<package name="students" namespace="/students" extends="default">
	<action name="*_*" class="action.{1}Action" method="{2}">
	<result name="Students_query_success">/students/Students_query_success.jsp </result>
	<result name="delete_success" type="chain">Students_query</result>
	<result name="add_success" >/students/Students_add_success.jsp</result>
	<result name="modify_success">/students/Students_modify.jsp</result>
	<result name="save_success" >/students/Students_modify_success.jsp</result>
	<result name="test_success">/students/test.jsp</result>
	<result name="test2_success">/students/zzKqzLineView.jsp</result>
	</action>
	</package>
</struts>    
